hawkdata/__init__.py
hawkdata/bond/cbond.py
hawkdata/fund/fund_basic.py
hawkdata/fund/fund_market_perf.py
hawkdata/index/china_index.py
hawkdata/index/global_index.py
hawkdata/macro/china_cpi.py
hawkdata/macro/china_gdp.py
hawkdata/stock/stock_us.py
hawkdata/utils/crawlers/__init__.py
hawkdata/utils/crawlers/cb_crawler.py
hawkdata/utils/crawlers/cnidx_crawler.py
hawkdata/utils/crawlers/csidx_crawler.py
hawkdata/utils/crawlers/cstats_crawler.py
hawkdata/utils/crawlers/em_crawler.py
hawkdata/utils/crawlers/headers.py
hawkdata/utils/crawlers/sf_crawler.py
hawkdata/utils/crawlers/web_crawler_base.py
hawkdata/utils/datasetx/__init__.py
hawkdata/utils/datasetx/datasetx.py
hawkdata/utils/datetimex/__init__.py
hawkdata/utils/datetimex/datetimex.py
hawkdata-0.0.10.dist-info/LICENSE
hawkdata-0.0.10.dist-info/METADATA
hawkdata-0.0.10.dist-info/WHEEL
hawkdata-0.0.10.dist-info/top_level.txt
hawkdata-0.0.10.dist-info/RECORD
