Metadata-Version: 2.1
Name: hawkdata
Version: 0.0.10
Summary: desc
Home-page: https://github.com/yzyx-data/hawkdata
Author: zachzhaozy@gmail.com
License: UNKNOWN
Project-URL: Issues, https://github.com/yzyx-data/hawkdata/issues
Platform: UNKNOWN
Classifier: Programming Language :: Python :: 3
Classifier: License :: OSI Approved :: GNU Affero General Public License v3 or later (AGPLv3+)
Classifier: Operating System :: OS Independent
Requires-Python: >=3.6
License-File: LICENSE
Requires-Dist: pandas ; python_version == "1.2.2"
Requires-Dist: numpy ; python_version == "1.20.1"
Requires-Dist: retrying ; python_version == "1.3.3"
Requires-Dist: pandarallel ; python_version == "1.5.3"
Requires-Dist: requests ; python_version == "2.24.0"
Requires-Dist: beautifulsoup4 ; python_version == "4.10.0"
Requires-Dist: cachetools ; python_version == "4.2.2"
Requires-Dist: tqdm ; python_version == "4.51.0"
